scathach
