Metadata-Version: 2.1
Name: scathach-api
Version: 1.3.9
Summary: An advanced NSFW wrapper, complete rewrite and overhaul of the original Fate/Lewd Order API.
Home-page: https://github.com/sinkaroid/scathach-api
Author: sinkaroid
Author-email: anakmancasan@gmail.com
License: MIT
Platform: UNKNOWN
